z3c.preference-2.0-py3.9-nspkg.pth
z3c/preference/README.rst
z3c/preference/__init__.py
z3c/preference/browser.py
z3c/preference/categories.rst
z3c/preference/configure.zcml
z3c/preference/form.pt
z3c/preference/ftesting.zcml
z3c/preference/i18n.py
z3c/preference/interfaces.py
z3c/preference/test-layout.pt
z3c/preference/testing.py
z3c/preference/tests.py
z3c.preference-2.0.dist-info/LICENSE.txt
z3c.preference-2.0.dist-info/METADATA
z3c.preference-2.0.dist-info/WHEEL
z3c.preference-2.0.dist-info/namespace_packages.txt
z3c.preference-2.0.dist-info/top_level.txt
z3c.preference-2.0.dist-info/RECORD
